SOURCE/commands/__init__.py
SOURCE/commands/cf_getproblem.py
SOURCE/commands/cf_openproblem.py
SOURCE/commands/cf_testproblem.py
SOURCE/commands/fetch_problem.py
SOURCE/commands/main.py
SOURCE/lib/__init__.py
SOURCE/lib/libcfp_errors.py
SOURCE/lib/libcfp_maintutils.py
SOURCE/modules/TEMP_workspace--see_README.py
SOURCE/modules/__init__.py
SOURCE/modules/cfp_config.py
SOURCE/modules/cfp_contest.py
SOURCE/modules/cfp_context.py
SOURCE/modules/cfp_errors.py
SOURCE/modules/cfp_logger.py
SOURCE/modules/cfp_pathutils.py
SOURCE/modules/cfp_problem.py
SOURCE/modules/cfp_session.py
SOURCE/modules/cfp_testcontext.py
SOURCE/modules/cfp_user.py
SOURCE/modules/cpf_contest.OLD.py
SOURCE/modules/nosetup.py
cf_pipeline-0.0.7.dist-info/METADATA
cf_pipeline-0.0.7.dist-info/WHEEL
cf_pipeline-0.0.7.dist-info/entry_points.txt
cf_pipeline-0.0.7.dist-info/top_level.txt
cf_pipeline-0.0.7.dist-info/RECORD
