Metadata-Version: 2.4
Name: cf-pipeline
Version: 0.0.7
Summary: A comprehensive Python API for Competitive Programming sites like Codeforces
Author-email: Nate Tolbert <ntolbertu85@gmail.com>
Project-URL: Homepage, https://github.com/lifemodder19135/cf-pipeline
Classifier: Programming Language :: Python :: 3
Classifier: Operating System :: OS Independent
Classifier: License :: OSI Approved :: MIT License
Requires-Python: >=3.10
